populse_mia/__init__.py
populse_mia/__main__.py
populse_mia/info.py
populse_mia/main.py
populse_mia/software_properties.py
populse_mia/test.py
populse_mia/data_manager/__init__.py
populse_mia/data_manager/data_history_inspect.py
populse_mia/data_manager/data_loader.py
populse_mia/data_manager/database_mia.py
populse_mia/data_manager/filter.py
populse_mia/data_manager/project.py
populse_mia/data_manager/project_properties.py
populse_mia/sources_images/B-W_LINEAR.png
populse_mia/sources_images/BLANK_ICON.png
populse_mia/sources_images/Blue-White.png
populse_mia/sources_images/Blue.png
populse_mia/sources_images/Green-White-linear.png
populse_mia/sources_images/LogoIRMaGe.png
populse_mia/sources_images/Logo_populse_mia_HR.jpeg
populse_mia/sources_images/Logo_populse_mia_LR.jpeg
populse_mia/sources_images/Logo_populse_square.jpg
populse_mia/sources_images/Protocol_record.png
populse_mia/sources_images/RAINBOW.png
populse_mia/sources_images/RED_TEMPERATURE.png
populse_mia/sources_images/Tool_Application.png
populse_mia/sources_images/Yellow-Red-White-Blue-Green.png
populse_mia/sources_images/Yellow-red.png
populse_mia/sources_images/__init__.py
populse_mia/sources_images/blue-red-bright-dark.png
populse_mia/sources_images/brain_mri.jpeg
populse_mia/sources_images/check.png
populse_mia/sources_images/create.png
populse_mia/sources_images/exit.png
populse_mia/sources_images/export.png
populse_mia/sources_images/garbage_collect.png
populse_mia/sources_images/gray_cross.png
populse_mia/sources_images/green_plus.png
populse_mia/sources_images/green_v.png
populse_mia/sources_images/icons-403.png
populse_mia/sources_images/init32.png
populse_mia/sources_images/open.png
populse_mia/sources_images/pause.png
populse_mia/sources_images/play.png
populse_mia/sources_images/plot.png
populse_mia/sources_images/pref.png
populse_mia/sources_images/red_cross.png
populse_mia/sources_images/red_cross32.png
populse_mia/sources_images/red_minus.png
populse_mia/sources_images/run32.png
populse_mia-2.6.0.dist-info/licenses/LICENSE
populse_mia-2.6.0.dist-info/METADATA
populse_mia-2.6.0.dist-info/WHEEL
populse_mia-2.6.0.dist-info/top_level.txt
populse_mia-2.6.0.dist-info/RECORD
