Metadata-Version: 2.4
Name: populse_mia
Version: 2.6.0
Summary: populse_mia
Home-page: http://populse.github.io/populse_mia
Author: Populse team
Author-email: Populse team <populse-support@univ-grenoble-alpes.fr>
License-Expression: CECILL-B
Project-URL: homepage, http://populse.github.io/populse_mia/
Project-URL: repository, https://github.com/populse/populse_mia
Platform: OS Independent
Classifier: Development Status :: 5 - Production/Stable
Classifier: Environment :: Console
Classifier: Intended Audience :: Developers
Classifier: Natural Language :: English
Classifier: Operating System :: OS Independent
Classifier: Programming Language :: Python :: 3 :: Only
Classifier: Programming Language :: Python :: 3.9
Classifier: Programming Language :: Python :: 3.10
Classifier: Programming Language :: Python :: 3.11
Classifier: Topic :: Software Development :: Libraries :: Python Modules
Requires-Python: >=3.9
License-File: LICENSE
Requires-Dist: capsul<3.0.0,>=2.5.0
Requires-Dist: cryptography
Requires-Dist: matplotlib
Requires-Dist: mia-processes<3.0.0,>=2.5.0
Requires-Dist: nibabel
Requires-Dist: nipype
Requires-Dist: pillow
Requires-Dist: populse-db<3.0.0,>=2.5.0
Requires-Dist: pre-commit
Requires-Dist: pyqt5
Requires-Dist: python-dateutil
Requires-Dist: pyyaml
Requires-Dist: scikit-image
Requires-Dist: scipy
Requires-Dist: snakeviz
Requires-Dist: soma-base<6.0.0,>=5.2.0
Requires-Dist: soma-workflow>=3.2.2
Requires-Dist: six>=1.13
Requires-Dist: traits
Provides-Extra: doc
Requires-Dist: sphinx>=1.0; extra == "doc"
Dynamic: author
Dynamic: home-page
Dynamic: license-file
Dynamic: platform
